layernext/__init__.py
layernext/automatic_analysis/__init__.py
layernext/automatic_analysis/automatic_analysis.py
layernext/automatic_analysis/automatic_analysis_interface.py
layernext/automatic_analysis/status_check_autoannotate_project.py
layernext/automatic_analysis/support.py
layernext/datalake/__init__.py
layernext/datalake/annotation.py
layernext/datalake/aws_s3_client.py
layernext/datalake/azure_client.py
layernext/datalake/constants.py
layernext/datalake/datalakeinterface.py
layernext/datalake/dataset.py
layernext/datalake/file_trash.py
layernext/datalake/file_upload.py
layernext/datalake/gcs_client.py
layernext/datalake/ground_truth.py
layernext/datalake/keys.py
layernext/datalake/label.py
layernext/datalake/logger.py
layernext/datalake/metadata.py
layernext/datalake/model_run.py
layernext/datalake/query.py
layernext/datalake/storage_client.py
layernext/datalake/storage_interface.py
layernext/datalake/storage_upload.py
layernext/dataset/__init__.py
layernext/dataset/dataset.py
layernext/dataset/datasetinterface.py
layernext/dataset/logger.py
layernext/dataset/sync.py
layernext/studio/__init__.py
layernext/studio/logger.py
layernext/studio/project.py
layernext/studio/studiointerface.py
layernext-2.3.4.dist-info/LICENSE
layernext-2.3.4.dist-info/METADATA
layernext-2.3.4.dist-info/WHEEL
layernext-2.3.4.dist-info/top_level.txt
layernext-2.3.4.dist-info/RECORD
